odoo/addons/sale_partner_selectable_option/README.rst
odoo/addons/sale_partner_selectable_option/__init__.py
odoo/addons/sale_partner_selectable_option/__manifest__.py
odoo/addons/sale_partner_selectable_option/data/ir_config_parameter.xml
odoo/addons/sale_partner_selectable_option/i18n/es.po
odoo/addons/sale_partner_selectable_option/i18n/it.po
odoo/addons/sale_partner_selectable_option/i18n/pt.po
odoo/addons/sale_partner_selectable_option/i18n/sale_partner_selectable_option.pot
odoo/addons/sale_partner_selectable_option/models/__init__.py
odoo/addons/sale_partner_selectable_option/models/res_partner.py
odoo/addons/sale_partner_selectable_option/models/sale_order.py
odoo/addons/sale_partner_selectable_option/readme/CONFIGURE.md
odoo/addons/sale_partner_selectable_option/readme/CONTRIBUTORS.md
odoo/addons/sale_partner_selectable_option/readme/DESCRIPTION.md
odoo/addons/sale_partner_selectable_option/readme/USAGE.md
odoo/addons/sale_partner_selectable_option/static/description/icon.png
odoo/addons/sale_partner_selectable_option/static/description/index.html
odoo/addons/sale_partner_selectable_option/tests/__init__.py
odoo/addons/sale_partner_selectable_option/tests/test_sale_partner_selectable_option.py
odoo/addons/sale_partner_selectable_option/views/res_partner_view.xml
odoo_addon_sale_partner_selectable_option-18.0.1.0.0.3.dist-info/METADATA
odoo_addon_sale_partner_selectable_option-18.0.1.0.0.3.dist-info/WHEEL
odoo_addon_sale_partner_selectable_option-18.0.1.0.0.3.dist-info/top_level.txt
odoo_addon_sale_partner_selectable_option-18.0.1.0.0.3.dist-info/RECORD
